{
  "id": "sGakuNs9mT4",
  "platform": "youtube",
  "url": "https://www.youtube.com/watch?v=sGakuNs9mT4",
  "title": "How to Speak So Well People Give You Money",
  "duration": 1289,
  "creator": "alexhormozi",
  "scraped_at": "2026-05-28",
  "wave": "wave-7-batch3",
  "scrape_tool": "yt-dlp",
  "rationale": "Oratory / sales (21 min). Likely contains voice/speech-pattern visuals (waveforms?), sales-call frameworks, conversation-tree diagrams. Could surface NEW patterns specific to verbal-skills content."
}